gssapi/__init__.py
gssapi/_utils.py
gssapi/_win_config.py
gssapi/creds.py
gssapi/exceptions.py
gssapi/mechs.py
gssapi/names.py
gssapi/py.typed
gssapi/sec_contexts.py
gssapi/raw/__init__.py
gssapi/raw/chan_bindings.cp314t-win_amd64.pyd
gssapi/raw/chan_bindings.pyi
gssapi/raw/creds.cp314t-win_amd64.pyd
gssapi/raw/creds.pyi
gssapi/raw/cython_converters.cp314t-win_amd64.pyd
gssapi/raw/exceptions.cp314t-win_amd64.pyd
gssapi/raw/exceptions.pyi
gssapi/raw/ext_cred_imp_exp.cp314t-win_amd64.pyd
gssapi/raw/ext_cred_imp_exp.pyi
gssapi/raw/ext_cred_store.cp314t-win_amd64.pyd
gssapi/raw/ext_cred_store.pyi
gssapi/raw/ext_dce.cp314t-win_amd64.pyd
gssapi/raw/ext_dce.pyi
gssapi/raw/ext_dce_aead.cp314t-win_amd64.pyd
gssapi/raw/ext_dce_aead.pyi
gssapi/raw/ext_ggf.cp314t-win_amd64.pyd
gssapi/raw/ext_ggf.pyi
gssapi/raw/ext_iov_mic.cp314t-win_amd64.pyd
gssapi/raw/ext_iov_mic.pyi
gssapi/raw/ext_krb5.cp314t-win_amd64.pyd
gssapi/raw/ext_krb5.pyi
gssapi/raw/ext_password.cp314t-win_amd64.pyd
gssapi/raw/ext_password.pyi
gssapi/raw/ext_password_add.pyi
gssapi/raw/ext_rfc4178.cp314t-win_amd64.pyd
gssapi/raw/ext_rfc4178.pyi
gssapi/raw/ext_rfc5587.cp314t-win_amd64.pyd
gssapi/raw/ext_rfc5587.pyi
gssapi/raw/ext_rfc5588.cp314t-win_amd64.pyd
gssapi/raw/ext_rfc5588.pyi
gssapi/raw/ext_rfc5801.cp314t-win_amd64.pyd
gssapi/raw/ext_rfc5801.pyi
gssapi/raw/ext_rfc6680.cp314t-win_amd64.pyd
gssapi/raw/ext_rfc6680.pyi
gssapi/raw/ext_rfc6680_comp_oid.cp314t-win_amd64.pyd
gssapi/raw/ext_rfc6680_comp_oid.pyi
gssapi/raw/ext_s4u.cp314t-win_amd64.pyd
gssapi/raw/ext_s4u.pyi
gssapi/raw/ext_set_cred_opt.cp314t-win_amd64.pyd
gssapi/raw/ext_set_cred_opt.pyi
gssapi/raw/mech_krb5.cp314t-win_amd64.pyd
gssapi/raw/mech_krb5.pyi
gssapi/raw/message.cp314t-win_amd64.pyd
gssapi/raw/message.pyi
gssapi/raw/misc.cp314t-win_amd64.pyd
gssapi/raw/misc.pyi
gssapi/raw/named_tuples.py
gssapi/raw/names.cp314t-win_amd64.pyd
gssapi/raw/names.pyi
gssapi/raw/oids.cp314t-win_amd64.pyd
gssapi/raw/oids.pyi
gssapi-1.11.1.dist-info/licenses/LICENSE.txt
gssapi-1.11.1.dist-info/METADATA
gssapi-1.11.1.dist-info/WHEEL
gssapi-1.11.1.dist-info/top_level.txt
gssapi-1.11.1.dist-info/RECORD
